easyql/__init__.py
easyql/database.py
easyql/field.py
easyql/model.py
easyql/payload.py
easyql/table.py
easyql/types.py
easyql-0.5.1.dist-info/METADATA
easyql-0.5.1.dist-info/WHEEL
easyql-0.5.1.dist-info/licenses/LICENSE
easyql-0.5.1.dist-info/RECORD
