Metadata-Version: 2.1
Name: easyql
Version: 0.5.1
Summary: An ORM library to interact with SQLite3 databases from python using Mongoose like APIs.
Project-URL: Homepage, https://github.com/gautamgiri-dev/easyql
Project-URL: Bug Tracker, https://github.com/gautamgiri-dev/easyql/issues
Author-email: Gautam Kumar Giri <personal.gautamgiri@gmail.com>
License-File: LICENSE
Classifier: License :: OSI Approved :: MIT License
Classifier: Operating System :: OS Independent
Classifier: Programming Language :: Python :: 3
Requires-Python: >=3.7
